{"Title":"Star Wars: Episode VIII - The Last Jedi","Year":"2017","Rated":"PG-13","Released":"15 Dec 2017","Runtime":"152 min","Genre":"Action, Adventure, Fantasy","Director":"Rian Johnson","Writer":"Rian Johnson, George Lucas","Actors":"Daisy Ridley, John Boyega, Mark Hamill","Plot":"Rey develops her abilities with the help of Luke Skywalker as the Resistance prepares for battle against the First Order.","Language":"English","Country":"United States","Awards":"Nominated for 4 Oscars. 26 wins \u0026 99 nominations total","Poster":"https://m.media-amazon.com/images/M/MV5BMjQ1MzcxNjg4N15BMl5BanBnXkFtZTgwNzgwMjY4MzI@._V1_SX300.jpg","Ratings":[{"Source":"Internet Movie Database","Value":"6.9/10"},{"Source":"Rotten Tomatoes","Value":"91%"},{"Source":"Metacritic","Value":"84/100"}],"Metascore":"84","imdbRating":"6.9","imdbVotes":"695,384","imdbID":"tt2527336","Type":"movie","BoxOffice":"$620,181,382","Response":"True"}